YTchannel/__init__.py
YTchannel-0.1.0.dist-info/LICENSE.txt
YTchannel-0.1.0.dist-info/METADATA
YTchannel-0.1.0.dist-info/WHEEL
YTchannel-0.1.0.dist-info/top_level.txt
YTchannel-0.1.0.dist-info/RECORD
