Metadata-Version: 2.1
Name: YTchannel
Version: 0.1.0
Summary: YouTube channel & video details extractor
Home-page: https://github.com/SanjayDevTech/YTchannel
Author: Sanjay Developer
Author-email: sureshsanjay805@gmail.com
License: UNKNOWN
Platform: UNKNOWN
Classifier: Programming Language :: Python :: 3
Classifier: License :: OSI Approved :: MIT License
Classifier: Operating System :: OS Independent
Requires-Python: >=3.6
